<?xml version="1.0" encoding="UTF-8"?>

<!-- generated on 2024-11-05 20:30:30 by Eclipse SUMO GUI Version 1.21.0
<sumoConfiguration xmlns:xsi="http://www.w3.org/2001/XMLSchema-instance" xsi:noNamespaceSchemaLocation="http://sumo.dlr.de/xsd/sumoConfiguration.xsd">

    <input>
        <net-file value="C:\Users\George Jiang\Desktop\Version 1\../../../../Windows/system32/2024-11-05-18-42-37/osm.net.xml.gz"/>
        <route-files value="C:\Users\George Jiang\Desktop\Version 1\../../../../Windows/system32/2024-11-05-18-42-37/osm.bicycle.trips.xml,C:\Users\George Jiang\Desktop\Version 1\../../../../Windows/system32/2024-11-05-18-42-37/osm.bus.trips.xml,C:\Users\George Jiang\Desktop\Version 1\../../../../Windows/system32/2024-11-05-18-42-37/osm.motorcycle.trips.xml,C:\Users\George Jiang\Desktop\Version 1\../../../../Windows/system32/2024-11-05-18-42-37/osm.passenger.trips.xml,C:\Users\George Jiang\Desktop\Version 1\../../../../Windows/system32/2024-11-05-18-42-37/osm.pedestrian.rou.xml,C:\Users\George Jiang\Desktop\Version 1\../../../../Windows/system32/2024-11-05-18-42-37/osm.rail.trips.xml,C:\Users\George Jiang\Desktop\Version 1\../../../../Windows/system32/2024-11-05-18-42-37/osm.rail_urban.trips.xml,C:\Users\George Jiang\Desktop\Version 1\../../../../Windows/system32/2024-11-05-18-42-37/osm.ship.trips.xml,C:\Users\George Jiang\Desktop\Version 1\../../../../Windows/system32/2024-11-05-18-42-37/osm.truck.trips.xml"/>
        <additional-files value="C:\Users\George Jiang\Desktop\Version 1\additional.xml"/>
    </input>

    <output>
        <fcd-output value="C:\Users\George Jiang\Desktop\Version 1\routes.xml"/>
        <summary-output value="C:\Users\George Jiang\Desktop\Version 1\summary.xml"/>
        <tripinfo-output value="C:\Users\George Jiang\Desktop\Version 1\tripinfo.xml"/>
        <stop-output value="C:\Users\George Jiang\Desktop\Version 1\stops.xml"/>
        <collision-output value="C:\Users\George Jiang\Desktop\Version 1\collisions.xml"/>
    </output>

    <processing>
        <ignore-route-errors value="true"/>
        <tls.actuated.jam-threshold value="30"/>
    </processing>

    <routing>
        <device.rerouting.adaptation-steps value="18"/>
        <device.rerouting.adaptation-interval value="10"/>
    </routing>

    <report>
        <verbose value="true"/>
        <duration-log.statistics value="true"/>
        <no-step-log value="true"/>
    </report>

    <gui_only>
        <gui-settings-file value="C:\Users\George Jiang\Desktop\Version 1\../../../../Windows/system32/2024-11-05-18-42-37/osm.view.xml"/>
    </gui_only>

</sumoConfiguration>
-->

<tlsStates xmlns:xsi="http://www.w3.org/2001/XMLSchema-instance" xsi:noNamespaceSchemaLocation="http://sumo.dlr.de/xsd/tlsstates_file.xsd">
    <tlsState time="0.00" id="cluster_61354584_7623094020_7629652945" programID="0" phase="0" state="ggrrGGr"/>
    <tlsState time="5.00" id="cluster_61354584_7623094020_7629652945" programID="0" phase="1" state="ggrrrrr"/>
    <tlsState time="10.00" id="cluster_61354584_7623094020_7629652945" programID="0" phase="2" state="yyrrrrr"/>
    <tlsState time="13.00" id="cluster_61354584_7623094020_7629652945" programID="0" phase="3" state="rrGGrrG"/>
    <tlsState time="18.00" id="cluster_61354584_7623094020_7629652945" programID="0" phase="4" state="rrGGrrr"/>
    <tlsState time="23.00" id="cluster_61354584_7623094020_7629652945" programID="0" phase="5" state="rryyrrr"/>
    <tlsState time="26.00" id="cluster_61354584_7623094020_7629652945" programID="0" phase="0" state="ggrrGGr"/>
    <tlsState time="31.00" id="cluster_61354584_7623094020_7629652945" programID="0" phase="1" state="ggrrrrr"/>
    <tlsState time="36.00" id="cluster_61354584_7623094020_7629652945" programID="0" phase="2" state="yyrrrrr"/>
    <tlsState time="39.00" id="cluster_61354584_7623094020_7629652945" programID="0" phase="3" state="rrGGrrG"/>
    <tlsState time="44.00" id="cluster_61354584_7623094020_7629652945" programID="0" phase="4" state="rrGGrrr"/>
    <tlsState time="49.00" id="cluster_61354584_7623094020_7629652945" programID="0" phase="5" state="rryyrrr"/>
    <tlsState time="52.00" id="cluster_61354584_7623094020_7629652945" programID="0" phase="0" state="ggrrGGr"/>
    <tlsState time="57.00" id="cluster_61354584_7623094020_7629652945" programID="0" phase="1" state="ggrrrrr"/>
    <tlsState time="62.00" id="cluster_61354584_7623094020_7629652945" programID="0" phase="2" state="yyrrrrr"/>
    <tlsState time="65.00" id="cluster_61354584_7623094020_7629652945" programID="0" phase="3" state="rrGGrrG"/>
    <tlsState time="70.00" id="cluster_61354584_7623094020_7629652945" programID="0" phase="4" state="rrGGrrr"/>
    <tlsState time="75.00" id="cluster_61354584_7623094020_7629652945" programID="0" phase="5" state="rryyrrr"/>
    <tlsState time="78.00" id="cluster_61354584_7623094020_7629652945" programID="0" phase="0" state="ggrrGGr"/>
    <tlsState time="84.00" id="cluster_61354584_7623094020_7629652945" programID="0" phase="1" state="ggrrrrr"/>
    <tlsState time="89.00" id="cluster_61354584_7623094020_7629652945" programID="0" phase="2" state="yyrrrrr"/>
    <tlsState time="92.00" id="cluster_61354584_7623094020_7629652945" programID="0" phase="3" state="rrGGrrG"/>
    <tlsState time="97.00" id="cluster_61354584_7623094020_7629652945" programID="0" phase="4" state="rrGGrrr"/>
    <tlsState time="102.00" id="cluster_61354584_7623094020_7629652945" programID="0" phase="5" state="rryyrrr"/>
    <tlsState time="105.00" id="cluster_61354584_7623094020_7629652945" programID="0" phase="0" state="ggrrGGr"/>
    <tlsState time="117.00" id="cluster_61354584_7623094020_7629652945" programID="0" phase="1" state="ggrrrrr"/>
    <tlsState time="122.00" id="cluster_61354584_7623094020_7629652945" programID="0" phase="2" state="yyrrrrr"/>
    <tlsState time="125.00" id="cluster_61354584_7623094020_7629652945" programID="0" phase="3" state="rrGGrrG"/>
    <tlsState time="130.00" id="cluster_61354584_7623094020_7629652945" programID="0" phase="4" state="rrGGrrr"/>
    <tlsState time="135.00" id="cluster_61354584_7623094020_7629652945" programID="0" phase="5" state="rryyrrr"/>
    <tlsState time="138.00" id="cluster_61354584_7623094020_7629652945" programID="0" phase="0" state="ggrrGGr"/>
    <tlsState time="143.00" id="cluster_61354584_7623094020_7629652945" programID="0" phase="1" state="ggrrrrr"/>
    <tlsState time="148.00" id="cluster_61354584_7623094020_7629652945" programID="0" phase="2" state="yyrrrrr"/>
    <tlsState time="151.00" id="cluster_61354584_7623094020_7629652945" programID="0" phase="3" state="rrGGrrG"/>
    <tlsState time="156.00" id="cluster_61354584_7623094020_7629652945" programID="0" phase="4" state="rrGGrrr"/>
    <tlsState time="161.00" id="cluster_61354584_7623094020_7629652945" programID="0" phase="5" state="rryyrrr"/>
    <tlsState time="164.00" id="cluster_61354584_7623094020_7629652945" programID="0" phase="0" state="ggrrGGr"/>
    <tlsState time="214.00" id="cluster_61354584_7623094020_7629652945" programID="0" phase="1" state="ggrrrrr"/>
    <tlsState time="219.00" id="cluster_61354584_7623094020_7629652945" programID="0" phase="2" state="yyrrrrr"/>
    <tlsState time="222.00" id="cluster_61354584_7623094020_7629652945" programID="0" phase="3" state="rrGGrrG"/>
    <tlsState time="231.00" id="cluster_61354584_7623094020_7629652945" programID="0" phase="4" state="rrGGrrr"/>
    <tlsState time="236.00" id="cluster_61354584_7623094020_7629652945" programID="0" phase="5" state="rryyrrr"/>
    <tlsState time="239.00" id="cluster_61354584_7623094020_7629652945" programID="0" phase="0" state="ggrrGGr"/>
    <tlsState time="261.00" id="cluster_61354584_7623094020_7629652945" programID="0" phase="1" state="ggrrrrr"/>
    <tlsState time="266.00" id="cluster_61354584_7623094020_7629652945" programID="0" phase="2" state="yyrrrrr"/>
    <tlsState time="269.00" id="cluster_61354584_7623094020_7629652945" programID="0" phase="3" state="rrGGrrG"/>
    <tlsState time="274.00" id="cluster_61354584_7623094020_7629652945" programID="0" phase="4" state="rrGGrrr"/>
    <tlsState time="279.00" id="cluster_61354584_7623094020_7629652945" programID="0" phase="5" state="rryyrrr"/>
    <tlsState time="282.00" id="cluster_61354584_7623094020_7629652945" programID="0" phase="0" state="ggrrGGr"/>
    <tlsState time="287.00" id="cluster_61354584_7623094020_7629652945" programID="0" phase="1" state="ggrrrrr"/>
    <tlsState time="292.00" id="cluster_61354584_7623094020_7629652945" programID="0" phase="2" state="yyrrrrr"/>
    <tlsState time="295.00" id="cluster_61354584_7623094020_7629652945" programID="0" phase="3" state="rrGGrrG"/>
    <tlsState time="300.00" id="cluster_61354584_7623094020_7629652945" programID="0" phase="4" state="rrGGrrr"/>
    <tlsState time="305.00" id="cluster_61354584_7623094020_7629652945" programID="0" phase="5" state="rryyrrr"/>
    <tlsState time="308.00" id="cluster_61354584_7623094020_7629652945" programID="0" phase="0" state="ggrrGGr"/>
    <tlsState time="313.00" id="cluster_61354584_7623094020_7629652945" programID="0" phase="1" state="ggrrrrr"/>
    <tlsState time="318.00" id="cluster_61354584_7623094020_7629652945" programID="0" phase="2" state="yyrrrrr"/>
    <tlsState time="321.00" id="cluster_61354584_7623094020_7629652945" programID="0" phase="3" state="rrGGrrG"/>
    <tlsState time="326.00" id="cluster_61354584_7623094020_7629652945" programID="0" phase="4" state="rrGGrrr"/>
    <tlsState time="331.00" id="cluster_61354584_7623094020_7629652945" programID="0" phase="5" state="rryyrrr"/>
    <tlsState time="334.00" id="cluster_61354584_7623094020_7629652945" programID="0" phase="0" state="ggrrGGr"/>
    <tlsState time="345.00" id="cluster_61354584_7623094020_7629652945" programID="0" phase="1" state="ggrrrrr"/>
    <tlsState time="350.00" id="cluster_61354584_7623094020_7629652945" programID="0" phase="2" state="yyrrrrr"/>
    <tlsState time="353.00" id="cluster_61354584_7623094020_7629652945" programID="0" phase="3" state="rrGGrrG"/>
    <tlsState time="361.00" id="cluster_61354584_7623094020_7629652945" programID="0" phase="4" state="rrGGrrr"/>
    <tlsState time="366.00" id="cluster_61354584_7623094020_7629652945" programID="0" phase="5" state="rryyrrr"/>
    <tlsState time="369.00" id="cluster_61354584_7623094020_7629652945" programID="0" phase="0" state="ggrrGGr"/>
    <tlsState time="374.00" id="cluster_61354584_7623094020_7629652945" programID="0" phase="1" state="ggrrrrr"/>
    <tlsState time="379.00" id="cluster_61354584_7623094020_7629652945" programID="0" phase="2" state="yyrrrrr"/>
    <tlsState time="382.00" id="cluster_61354584_7623094020_7629652945" programID="0" phase="3" state="rrGGrrG"/>
    <tlsState time="387.00" id="cluster_61354584_7623094020_7629652945" programID="0" phase="4" state="rrGGrrr"/>
    <tlsState time="392.00" id="cluster_61354584_7623094020_7629652945" programID="0" phase="5" state="rryyrrr"/>
    <tlsState time="395.00" id="cluster_61354584_7623094020_7629652945" programID="0" phase="0" state="ggrrGGr"/>
    <tlsState time="400.00" id="cluster_61354584_7623094020_7629652945" programID="0" phase="1" state="ggrrrrr"/>
    <tlsState time="405.00" id="cluster_61354584_7623094020_7629652945" programID="0" phase="2" state="yyrrrrr"/>
    <tlsState time="408.00" id="cluster_61354584_7623094020_7629652945" programID="0" phase="3" state="rrGGrrG"/>
    <tlsState time="433.00" id="cluster_61354584_7623094020_7629652945" programID="0" phase="4" state="rrGGrrr"/>
    <tlsState time="438.00" id="cluster_61354584_7623094020_7629652945" programID="0" phase="5" state="rryyrrr"/>
    <tlsState time="441.00" id="cluster_61354584_7623094020_7629652945" programID="0" phase="0" state="ggrrGGr"/>
    <tlsState time="446.00" id="cluster_61354584_7623094020_7629652945" programID="0" phase="1" state="ggrrrrr"/>
    <tlsState time="451.00" id="cluster_61354584_7623094020_7629652945" programID="0" phase="2" state="yyrrrrr"/>
    <tlsState time="454.00" id="cluster_61354584_7623094020_7629652945" programID="0" phase="3" state="rrGGrrG"/>
    <tlsState time="459.00" id="cluster_61354584_7623094020_7629652945" programID="0" phase="4" state="rrGGrrr"/>
    <tlsState time="464.00" id="cluster_61354584_7623094020_7629652945" programID="0" phase="5" state="rryyrrr"/>
    <tlsState time="467.00" id="cluster_61354584_7623094020_7629652945" programID="0" phase="0" state="ggrrGGr"/>
    <tlsState time="472.00" id="cluster_61354584_7623094020_7629652945" programID="0" phase="1" state="ggrrrrr"/>
    <tlsState time="477.00" id="cluster_61354584_7623094020_7629652945" programID="0" phase="2" state="yyrrrrr"/>
    <tlsState time="480.00" id="cluster_61354584_7623094020_7629652945" programID="0" phase="3" state="rrGGrrG"/>
    <tlsState time="485.00" id="cluster_61354584_7623094020_7629652945" programID="0" phase="4" state="rrGGrrr"/>
    <tlsState time="490.00" id="cluster_61354584_7623094020_7629652945" programID="0" phase="5" state="rryyrrr"/>
    <tlsState time="493.00" id="cluster_61354584_7623094020_7629652945" programID="0" phase="0" state="ggrrGGr"/>
    <tlsState time="498.00" id="cluster_61354584_7623094020_7629652945" programID="0" phase="1" state="ggrrrrr"/>
    <tlsState time="503.00" id="cluster_61354584_7623094020_7629652945" programID="0" phase="2" state="yyrrrrr"/>
    <tlsState time="506.00" id="cluster_61354584_7623094020_7629652945" programID="0" phase="3" state="rrGGrrG"/>
    <tlsState time="511.00" id="cluster_61354584_7623094020_7629652945" programID="0" phase="4" state="rrGGrrr"/>
    <tlsState time="516.00" id="cluster_61354584_7623094020_7629652945" programID="0" phase="5" state="rryyrrr"/>
    <tlsState time="519.00" id="cluster_61354584_7623094020_7629652945" programID="0" phase="0" state="ggrrGGr"/>
    <tlsState time="524.00" id="cluster_61354584_7623094020_7629652945" programID="0" phase="1" state="ggrrrrr"/>
    <tlsState time="529.00" id="cluster_61354584_7623094020_7629652945" programID="0" phase="2" state="yyrrrrr"/>
    <tlsState time="532.00" id="cluster_61354584_7623094020_7629652945" programID="0" phase="3" state="rrGGrrG"/>
    <tlsState time="537.00" id="cluster_61354584_7623094020_7629652945" programID="0" phase="4" state="rrGGrrr"/>
    <tlsState time="542.00" id="cluster_61354584_7623094020_7629652945" programID="0" phase="5" state="rryyrrr"/>
    <tlsState time="545.00" id="cluster_61354584_7623094020_7629652945" programID="0" phase="0" state="ggrrGGr"/>
    <tlsState time="550.00" id="cluster_61354584_7623094020_7629652945" programID="0" phase="1" state="ggrrrrr"/>
    <tlsState time="555.00" id="cluster_61354584_7623094020_7629652945" programID="0" phase="2" state="yyrrrrr"/>
    <tlsState time="558.00" id="cluster_61354584_7623094020_7629652945" programID="0" phase="3" state="rrGGrrG"/>
    <tlsState time="563.00" id="cluster_61354584_7623094020_7629652945" programID="0" phase="4" state="rrGGrrr"/>
    <tlsState time="568.00" id="cluster_61354584_7623094020_7629652945" programID="0" phase="5" state="rryyrrr"/>
    <tlsState time="571.00" id="cluster_61354584_7623094020_7629652945" programID="0" phase="0" state="ggrrGGr"/>
    <tlsState time="576.00" id="cluster_61354584_7623094020_7629652945" programID="0" phase="1" state="ggrrrrr"/>
    <tlsState time="581.00" id="cluster_61354584_7623094020_7629652945" programID="0" phase="2" state="yyrrrrr"/>
    <tlsState time="584.00" id="cluster_61354584_7623094020_7629652945" programID="0" phase="3" state="rrGGrrG"/>
    <tlsState time="589.00" id="cluster_61354584_7623094020_7629652945" programID="0" phase="4" state="rrGGrrr"/>
    <tlsState time="594.00" id="cluster_61354584_7623094020_7629652945" programID="0" phase="5" state="rryyrrr"/>
    <tlsState time="597.00" id="cluster_61354584_7623094020_7629652945" programID="0" phase="0" state="ggrrGGr"/>
    <tlsState time="602.00" id="cluster_61354584_7623094020_7629652945" programID="0" phase="1" state="ggrrrrr"/>
    <tlsState time="607.00" id="cluster_61354584_7623094020_7629652945" programID="0" phase="2" state="yyrrrrr"/>
    <tlsState time="610.00" id="cluster_61354584_7623094020_7629652945" programID="0" phase="3" state="rrGGrrG"/>
    <tlsState time="615.00" id="cluster_61354584_7623094020_7629652945" programID="0" phase="4" state="rrGGrrr"/>
    <tlsState time="620.00" id="cluster_61354584_7623094020_7629652945" programID="0" phase="5" state="rryyrrr"/>
    <tlsState time="623.00" id="cluster_61354584_7623094020_7629652945" programID="0" phase="0" state="ggrrGGr"/>
    <tlsState time="672.00" id="cluster_61354584_7623094020_7629652945" programID="0" phase="1" state="ggrrrrr"/>
    <tlsState time="677.00" id="cluster_61354584_7623094020_7629652945" programID="0" phase="2" state="yyrrrrr"/>
    <tlsState time="680.00" id="cluster_61354584_7623094020_7629652945" programID="0" phase="3" state="rrGGrrG"/>
    <tlsState time="709.00" id="cluster_61354584_7623094020_7629652945" programID="0" phase="4" state="rrGGrrr"/>
    <tlsState time="714.00" id="cluster_61354584_7623094020_7629652945" programID="0" phase="5" state="rryyrrr"/>
    <tlsState time="717.00" id="cluster_61354584_7623094020_7629652945" programID="0" phase="0" state="ggrrGGr"/>
    <tlsState time="722.00" id="cluster_61354584_7623094020_7629652945" programID="0" phase="1" state="ggrrrrr"/>
    <tlsState time="727.00" id="cluster_61354584_7623094020_7629652945" programID="0" phase="2" state="yyrrrrr"/>
    <tlsState time="730.00" id="cluster_61354584_7623094020_7629652945" programID="0" phase="3" state="rrGGrrG"/>
    <tlsState time="735.00" id="cluster_61354584_7623094020_7629652945" programID="0" phase="4" state="rrGGrrr"/>
    <tlsState time="740.00" id="cluster_61354584_7623094020_7629652945" programID="0" phase="5" state="rryyrrr"/>
    <tlsState time="743.00" id="cluster_61354584_7623094020_7629652945" programID="0" phase="0" state="ggrrGGr"/>
    <tlsState time="748.00" id="cluster_61354584_7623094020_7629652945" programID="0" phase="1" state="ggrrrrr"/>
    <tlsState time="753.00" id="cluster_61354584_7623094020_7629652945" programID="0" phase="2" state="yyrrrrr"/>
    <tlsState time="756.00" id="cluster_61354584_7623094020_7629652945" programID="0" phase="3" state="rrGGrrG"/>
    <tlsState time="761.00" id="cluster_61354584_7623094020_7629652945" programID="0" phase="4" state="rrGGrrr"/>
    <tlsState time="766.00" id="cluster_61354584_7623094020_7629652945" programID="0" phase="5" state="rryyrrr"/>
    <tlsState time="769.00" id="cluster_61354584_7623094020_7629652945" programID="0" phase="0" state="ggrrGGr"/>
    <tlsState time="774.00" id="cluster_61354584_7623094020_7629652945" programID="0" phase="1" state="ggrrrrr"/>
    <tlsState time="779.00" id="cluster_61354584_7623094020_7629652945" programID="0" phase="2" state="yyrrrrr"/>
    <tlsState time="782.00" id="cluster_61354584_7623094020_7629652945" programID="0" phase="3" state="rrGGrrG"/>
    <tlsState time="787.00" id="cluster_61354584_7623094020_7629652945" programID="0" phase="4" state="rrGGrrr"/>
    <tlsState time="792.00" id="cluster_61354584_7623094020_7629652945" programID="0" phase="5" state="rryyrrr"/>
    <tlsState time="795.00" id="cluster_61354584_7623094020_7629652945" programID="0" phase="0" state="ggrrGGr"/>
    <tlsState time="800.00" id="cluster_61354584_7623094020_7629652945" programID="0" phase="1" state="ggrrrrr"/>
    <tlsState time="805.00" id="cluster_61354584_7623094020_7629652945" programID="0" phase="2" state="yyrrrrr"/>
    <tlsState time="808.00" id="cluster_61354584_7623094020_7629652945" programID="0" phase="3" state="rrGGrrG"/>
    <tlsState time="813.00" id="cluster_61354584_7623094020_7629652945" programID="0" phase="4" state="rrGGrrr"/>
    <tlsState time="818.00" id="cluster_61354584_7623094020_7629652945" programID="0" phase="5" state="rryyrrr"/>
    <tlsState time="821.00" id="cluster_61354584_7623094020_7629652945" programID="0" phase="0" state="ggrrGGr"/>
    <tlsState time="826.00" id="cluster_61354584_7623094020_7629652945" programID="0" phase="1" state="ggrrrrr"/>
    <tlsState time="831.00" id="cluster_61354584_7623094020_7629652945" programID="0" phase="2" state="yyrrrrr"/>
    <tlsState time="834.00" id="cluster_61354584_7623094020_7629652945" programID="0" phase="3" state="rrGGrrG"/>
    <tlsState time="839.00" id="cluster_61354584_7623094020_7629652945" programID="0" phase="4" state="rrGGrrr"/>
    <tlsState time="844.00" id="cluster_61354584_7623094020_7629652945" programID="0" phase="5" state="rryyrrr"/>
    <tlsState time="847.00" id="cluster_61354584_7623094020_7629652945" programID="0" phase="0" state="ggrrGGr"/>
    <tlsState time="852.00" id="cluster_61354584_7623094020_7629652945" programID="0" phase="1" state="ggrrrrr"/>
    <tlsState time="857.00" id="cluster_61354584_7623094020_7629652945" programID="0" phase="2" state="yyrrrrr"/>
    <tlsState time="860.00" id="cluster_61354584_7623094020_7629652945" programID="0" phase="3" state="rrGGrrG"/>
    <tlsState time="865.00" id="cluster_61354584_7623094020_7629652945" programID="0" phase="4" state="rrGGrrr"/>
    <tlsState time="870.00" id="cluster_61354584_7623094020_7629652945" programID="0" phase="5" state="rryyrrr"/>
    <tlsState time="873.00" id="cluster_61354584_7623094020_7629652945" programID="0" phase="0" state="ggrrGGr"/>
    <tlsState time="878.00" id="cluster_61354584_7623094020_7629652945" programID="0" phase="1" state="ggrrrrr"/>
    <tlsState time="883.00" id="cluster_61354584_7623094020_7629652945" programID="0" phase="2" state="yyrrrrr"/>
    <tlsState time="886.00" id="cluster_61354584_7623094020_7629652945" programID="0" phase="3" state="rrGGrrG"/>
    <tlsState time="891.00" id="cluster_61354584_7623094020_7629652945" programID="0" phase="4" state="rrGGrrr"/>
    <tlsState time="896.00" id="cluster_61354584_7623094020_7629652945" programID="0" phase="5" state="rryyrrr"/>
    <tlsState time="899.00" id="cluster_61354584_7623094020_7629652945" programID="0" phase="0" state="ggrrGGr"/>
    <tlsState time="904.00" id="cluster_61354584_7623094020_7629652945" programID="0" phase="1" state="ggrrrrr"/>
    <tlsState time="909.00" id="cluster_61354584_7623094020_7629652945" programID="0" phase="2" state="yyrrrrr"/>
    <tlsState time="912.00" id="cluster_61354584_7623094020_7629652945" programID="0" phase="3" state="rrGGrrG"/>
    <tlsState time="920.00" id="cluster_61354584_7623094020_7629652945" programID="0" phase="4" state="rrGGrrr"/>
    <tlsState time="925.00" id="cluster_61354584_7623094020_7629652945" programID="0" phase="5" state="rryyrrr"/>
    <tlsState time="928.00" id="cluster_61354584_7623094020_7629652945" programID="0" phase="0" state="ggrrGGr"/>
    <tlsState time="933.00" id="cluster_61354584_7623094020_7629652945" programID="0" phase="1" state="ggrrrrr"/>
    <tlsState time="938.00" id="cluster_61354584_7623094020_7629652945" programID="0" phase="2" state="yyrrrrr"/>
    <tlsState time="941.00" id="cluster_61354584_7623094020_7629652945" programID="0" phase="3" state="rrGGrrG"/>
    <tlsState time="989.00" id="cluster_61354584_7623094020_7629652945" programID="0" phase="4" state="rrGGrrr"/>
    <tlsState time="994.00" id="cluster_61354584_7623094020_7629652945" programID="0" phase="5" state="rryyrrr"/>
    <tlsState time="997.00" id="cluster_61354584_7623094020_7629652945" programID="0" phase="0" state="ggrrGGr"/>
    <tlsState time="1002.00" id="cluster_61354584_7623094020_7629652945" programID="0" phase="1" state="ggrrrrr"/>
    <tlsState time="1007.00" id="cluster_61354584_7623094020_7629652945" programID="0" phase="2" state="yyrrrrr"/>
    <tlsState time="1010.00" id="cluster_61354584_7623094020_7629652945" programID="0" phase="3" state="rrGGrrG"/>
    <tlsState time="1015.00" id="cluster_61354584_7623094020_7629652945" programID="0" phase="4" state="rrGGrrr"/>
    <tlsState time="1020.00" id="cluster_61354584_7623094020_7629652945" programID="0" phase="5" state="rryyrrr"/>
    <tlsState time="1023.00" id="cluster_61354584_7623094020_7629652945" programID="0" phase="0" state="ggrrGGr"/>
    <tlsState time="1035.00" id="cluster_61354584_7623094020_7629652945" programID="0" phase="1" state="ggrrrrr"/>
    <tlsState time="1040.00" id="cluster_61354584_7623094020_7629652945" programID="0" phase="2" state="yyrrrrr"/>
    <tlsState time="1043.00" id="cluster_61354584_7623094020_7629652945" programID="0" phase="3" state="rrGGrrG"/>
    <tlsState time="1048.00" id="cluster_61354584_7623094020_7629652945" programID="0" phase="4" state="rrGGrrr"/>
    <tlsState time="1053.00" id="cluster_61354584_7623094020_7629652945" programID="0" phase="5" state="rryyrrr"/>
    <tlsState time="1056.00" id="cluster_61354584_7623094020_7629652945" programID="0" phase="0" state="ggrrGGr"/>
    <tlsState time="1061.00" id="cluster_61354584_7623094020_7629652945" programID="0" phase="1" state="ggrrrrr"/>
    <tlsState time="1066.00" id="cluster_61354584_7623094020_7629652945" programID="0" phase="2" state="yyrrrrr"/>
    <tlsState time="1069.00" id="cluster_61354584_7623094020_7629652945" programID="0" phase="3" state="rrGGrrG"/>
    <tlsState time="1074.00" id="cluster_61354584_7623094020_7629652945" programID="0" phase="4" state="rrGGrrr"/>
    <tlsState time="1079.00" id="cluster_61354584_7623094020_7629652945" programID="0" phase="5" state="rryyrrr"/>
    <tlsState time="1082.00" id="cluster_61354584_7623094020_7629652945" programID="0" phase="0" state="ggrrGGr"/>
    <tlsState time="1087.00" id="cluster_61354584_7623094020_7629652945" programID="0" phase="1" state="ggrrrrr"/>
    <tlsState time="1092.00" id="cluster_61354584_7623094020_7629652945" programID="0" phase="2" state="yyrrrrr"/>
    <tlsState time="1095.00" id="cluster_61354584_7623094020_7629652945" programID="0" phase="3" state="rrGGrrG"/>
    <tlsState time="1100.00" id="cluster_61354584_7623094020_7629652945" programID="0" phase="4" state="rrGGrrr"/>
    <tlsState time="1105.00" id="cluster_61354584_7623094020_7629652945" programID="0" phase="5" state="rryyrrr"/>
    <tlsState time="1108.00" id="cluster_61354584_7623094020_7629652945" programID="0" phase="0" state="ggrrGGr"/>
    <tlsState time="1113.00" id="cluster_61354584_7623094020_7629652945" programID="0" phase="1" state="ggrrrrr"/>
    <tlsState time="1118.00" id="cluster_61354584_7623094020_7629652945" programID="0" phase="2" state="yyrrrrr"/>
    <tlsState time="1121.00" id="cluster_61354584_7623094020_7629652945" programID="0" phase="3" state="rrGGrrG"/>
    <tlsState time="1126.00" id="cluster_61354584_7623094020_7629652945" programID="0" phase="4" state="rrGGrrr"/>
    <tlsState time="1131.00" id="cluster_61354584_7623094020_7629652945" programID="0" phase="5" state="rryyrrr"/>
    <tlsState time="1134.00" id="cluster_61354584_7623094020_7629652945" programID="0" phase="0" state="ggrrGGr"/>
    <tlsState time="1139.00" id="cluster_61354584_7623094020_7629652945" programID="0" phase="1" state="ggrrrrr"/>
    <tlsState time="1144.00" id="cluster_61354584_7623094020_7629652945" programID="0" phase="2" state="yyrrrrr"/>
    <tlsState time="1147.00" id="cluster_61354584_7623094020_7629652945" programID="0" phase="3" state="rrGGrrG"/>
    <tlsState time="1152.00" id="cluster_61354584_7623094020_7629652945" programID="0" phase="4" state="rrGGrrr"/>
    <tlsState time="1157.00" id="cluster_61354584_7623094020_7629652945" programID="0" phase="5" state="rryyrrr"/>
    <tlsState time="1160.00" id="cluster_61354584_7623094020_7629652945" programID="0" phase="0" state="ggrrGGr"/>
    <tlsState time="1165.00" id="cluster_61354584_7623094020_7629652945" programID="0" phase="1" state="ggrrrrr"/>
    <tlsState time="1170.00" id="cluster_61354584_7623094020_7629652945" programID="0" phase="2" state="yyrrrrr"/>
    <tlsState time="1173.00" id="cluster_61354584_7623094020_7629652945" programID="0" phase="3" state="rrGGrrG"/>
    <tlsState time="1178.00" id="cluster_61354584_7623094020_7629652945" programID="0" phase="4" state="rrGGrrr"/>
    <tlsState time="1183.00" id="cluster_61354584_7623094020_7629652945" programID="0" phase="5" state="rryyrrr"/>
    <tlsState time="1186.00" id="cluster_61354584_7623094020_7629652945" programID="0" phase="0" state="ggrrGGr"/>
    <tlsState time="1191.00" id="cluster_61354584_7623094020_7629652945" programID="0" phase="1" state="ggrrrrr"/>
    <tlsState time="1196.00" id="cluster_61354584_7623094020_7629652945" programID="0" phase="2" state="yyrrrrr"/>
    <tlsState time="1199.00" id="cluster_61354584_7623094020_7629652945" programID="0" phase="3" state="rrGGrrG"/>
    <tlsState time="1204.00" id="cluster_61354584_7623094020_7629652945" programID="0" phase="4" state="rrGGrrr"/>
    <tlsState time="1209.00" id="cluster_61354584_7623094020_7629652945" programID="0" phase="5" state="rryyrrr"/>
    <tlsState time="1212.00" id="cluster_61354584_7623094020_7629652945" programID="0" phase="0" state="ggrrGGr"/>
    <tlsState time="1217.00" id="cluster_61354584_7623094020_7629652945" programID="0" phase="1" state="ggrrrrr"/>
    <tlsState time="1222.00" id="cluster_61354584_7623094020_7629652945" programID="0" phase="2" state="yyrrrrr"/>
    <tlsState time="1225.00" id="cluster_61354584_7623094020_7629652945" programID="0" phase="3" state="rrGGrrG"/>
    <tlsState time="1230.00" id="cluster_61354584_7623094020_7629652945" programID="0" phase="4" state="rrGGrrr"/>
    <tlsState time="1235.00" id="cluster_61354584_7623094020_7629652945" programID="0" phase="5" state="rryyrrr"/>
    <tlsState time="1238.00" id="cluster_61354584_7623094020_7629652945" programID="0" phase="0" state="ggrrGGr"/>
    <tlsState time="1243.00" id="cluster_61354584_7623094020_7629652945" programID="0" phase="1" state="ggrrrrr"/>
    <tlsState time="1248.00" id="cluster_61354584_7623094020_7629652945" programID="0" phase="2" state="yyrrrrr"/>
    <tlsState time="1251.00" id="cluster_61354584_7623094020_7629652945" programID="0" phase="3" state="rrGGrrG"/>
    <tlsState time="1256.00" id="cluster_61354584_7623094020_7629652945" programID="0" phase="4" state="rrGGrrr"/>
    <tlsState time="1261.00" id="cluster_61354584_7623094020_7629652945" programID="0" phase="5" state="rryyrrr"/>
    <tlsState time="1264.00" id="cluster_61354584_7623094020_7629652945" programID="0" phase="0" state="ggrrGGr"/>
    <tlsState time="1269.00" id="cluster_61354584_7623094020_7629652945" programID="0" phase="1" state="ggrrrrr"/>
    <tlsState time="1274.00" id="cluster_61354584_7623094020_7629652945" programID="0" phase="2" state="yyrrrrr"/>
    <tlsState time="1277.00" id="cluster_61354584_7623094020_7629652945" programID="0" phase="3" state="rrGGrrG"/>
    <tlsState time="1286.00" id="cluster_61354584_7623094020_7629652945" programID="0" phase="4" state="rrGGrrr"/>
    <tlsState time="1291.00" id="cluster_61354584_7623094020_7629652945" programID="0" phase="5" state="rryyrrr"/>
    <tlsState time="1294.00" id="cluster_61354584_7623094020_7629652945" programID="0" phase="0" state="ggrrGGr"/>
    <tlsState time="1299.00" id="cluster_61354584_7623094020_7629652945" programID="0" phase="1" state="ggrrrrr"/>
    <tlsState time="1304.00" id="cluster_61354584_7623094020_7629652945" programID="0" phase="2" state="yyrrrrr"/>
    <tlsState time="1307.00" id="cluster_61354584_7623094020_7629652945" programID="0" phase="3" state="rrGGrrG"/>
    <tlsState time="1312.00" id="cluster_61354584_7623094020_7629652945" programID="0" phase="4" state="rrGGrrr"/>
    <tlsState time="1317.00" id="cluster_61354584_7623094020_7629652945" programID="0" phase="5" state="rryyrrr"/>
    <tlsState time="1320.00" id="cluster_61354584_7623094020_7629652945" programID="0" phase="0" state="ggrrGGr"/>
    <tlsState time="1325.00" id="cluster_61354584_7623094020_7629652945" programID="0" phase="1" state="ggrrrrr"/>
    <tlsState time="1330.00" id="cluster_61354584_7623094020_7629652945" programID="0" phase="2" state="yyrrrrr"/>
    <tlsState time="1333.00" id="cluster_61354584_7623094020_7629652945" programID="0" phase="3" state="rrGGrrG"/>
    <tlsState time="1338.00" id="cluster_61354584_7623094020_7629652945" programID="0" phase="4" state="rrGGrrr"/>
    <tlsState time="1343.00" id="cluster_61354584_7623094020_7629652945" programID="0" phase="5" state="rryyrrr"/>
    <tlsState time="1346.00" id="cluster_61354584_7623094020_7629652945" programID="0" phase="0" state="ggrrGGr"/>
    <tlsState time="1369.00" id="cluster_61354584_7623094020_7629652945" programID="0" phase="1" state="ggrrrrr"/>
    <tlsState time="1374.00" id="cluster_61354584_7623094020_7629652945" programID="0" phase="2" state="yyrrrrr"/>
    <tlsState time="1377.00" id="cluster_61354584_7623094020_7629652945" programID="0" phase="3" state="rrGGrrG"/>
    <tlsState time="1382.00" id="cluster_61354584_7623094020_7629652945" programID="0" phase="4" state="rrGGrrr"/>
    <tlsState time="1387.00" id="cluster_61354584_7623094020_7629652945" programID="0" phase="5" state="rryyrrr"/>
    <tlsState time="1390.00" id="cluster_61354584_7623094020_7629652945" programID="0" phase="0" state="ggrrGGr"/>
    <tlsState time="1395.00" id="cluster_61354584_7623094020_7629652945" programID="0" phase="1" state="ggrrrrr"/>
    <tlsState time="1400.00" id="cluster_61354584_7623094020_7629652945" programID="0" phase="2" state="yyrrrrr"/>
    <tlsState time="1403.00" id="cluster_61354584_7623094020_7629652945" programID="0" phase="3" state="rrGGrrG"/>
    <tlsState time="1408.00" id="cluster_61354584_7623094020_7629652945" programID="0" phase="4" state="rrGGrrr"/>
    <tlsState time="1413.00" id="cluster_61354584_7623094020_7629652945" programID="0" phase="5" state="rryyrrr"/>
    <tlsState time="1416.00" id="cluster_61354584_7623094020_7629652945" programID="0" phase="0" state="ggrrGGr"/>
    <tlsState time="1421.00" id="cluster_61354584_7623094020_7629652945" programID="0" phase="1" state="ggrrrrr"/>
    <tlsState time="1426.00" id="cluster_61354584_7623094020_7629652945" programID="0" phase="2" state="yyrrrrr"/>
    <tlsState time="1429.00" id="cluster_61354584_7623094020_7629652945" programID="0" phase="3" state="rrGGrrG"/>
    <tlsState time="1434.00" id="cluster_61354584_7623094020_7629652945" programID="0" phase="4" state="rrGGrrr"/>
    <tlsState time="1439.00" id="cluster_61354584_7623094020_7629652945" programID="0" phase="5" state="rryyrrr"/>
    <tlsState time="1442.00" id="cluster_61354584_7623094020_7629652945" programID="0" phase="0" state="ggrrGGr"/>
    <tlsState time="1447.00" id="cluster_61354584_7623094020_7629652945" programID="0" phase="1" state="ggrrrrr"/>
    <tlsState time="1452.00" id="cluster_61354584_7623094020_7629652945" programID="0" phase="2" state="yyrrrrr"/>
    <tlsState time="1455.00" id="cluster_61354584_7623094020_7629652945" programID="0" phase="3" state="rrGGrrG"/>
    <tlsState time="1460.00" id="cluster_61354584_7623094020_7629652945" programID="0" phase="4" state="rrGGrrr"/>
    <tlsState time="1465.00" id="cluster_61354584_7623094020_7629652945" programID="0" phase="5" state="rryyrrr"/>
    <tlsState time="1468.00" id="cluster_61354584_7623094020_7629652945" programID="0" phase="0" state="ggrrGGr"/>
    <tlsState time="1473.00" id="cluster_61354584_7623094020_7629652945" programID="0" phase="1" state="ggrrrrr"/>
    <tlsState time="1478.00" id="cluster_61354584_7623094020_7629652945" programID="0" phase="2" state="yyrrrrr"/>
    <tlsState time="1481.00" id="cluster_61354584_7623094020_7629652945" programID="0" phase="3" state="rrGGrrG"/>
    <tlsState time="1486.00" id="cluster_61354584_7623094020_7629652945" programID="0" phase="4" state="rrGGrrr"/>
    <tlsState time="1491.00" id="cluster_61354584_7623094020_7629652945" programID="0" phase="5" state="rryyrrr"/>
    <tlsState time="1494.00" id="cluster_61354584_7623094020_7629652945" programID="0" phase="0" state="ggrrGGr"/>
    <tlsState time="1499.00" id="cluster_61354584_7623094020_7629652945" programID="0" phase="1" state="ggrrrrr"/>
    <tlsState time="1504.00" id="cluster_61354584_7623094020_7629652945" programID="0" phase="2" state="yyrrrrr"/>
    <tlsState time="1507.00" id="cluster_61354584_7623094020_7629652945" programID="0" phase="3" state="rrGGrrG"/>
    <tlsState time="1512.00" id="cluster_61354584_7623094020_7629652945" programID="0" phase="4" state="rrGGrrr"/>
    <tlsState time="1517.00" id="cluster_61354584_7623094020_7629652945" programID="0" phase="5" state="rryyrrr"/>
    <tlsState time="1520.00" id="cluster_61354584_7623094020_7629652945" programID="0" phase="0" state="ggrrGGr"/>
    <tlsState time="1525.00" id="cluster_61354584_7623094020_7629652945" programID="0" phase="1" state="ggrrrrr"/>
    <tlsState time="1530.00" id="cluster_61354584_7623094020_7629652945" programID="0" phase="2" state="yyrrrrr"/>
    <tlsState time="1533.00" id="cluster_61354584_7623094020_7629652945" programID="0" phase="3" state="rrGGrrG"/>
    <tlsState time="1550.00" id="cluster_61354584_7623094020_7629652945" programID="0" phase="4" state="rrGGrrr"/>
    <tlsState time="1555.00" id="cluster_61354584_7623094020_7629652945" programID="0" phase="5" state="rryyrrr"/>
    <tlsState time="1558.00" id="cluster_61354584_7623094020_7629652945" programID="0" phase="0" state="ggrrGGr"/>
    <tlsState time="1563.00" id="cluster_61354584_7623094020_7629652945" programID="0" phase="1" state="ggrrrrr"/>
    <tlsState time="1568.00" id="cluster_61354584_7623094020_7629652945" programID="0" phase="2" state="yyrrrrr"/>
    <tlsState time="1571.00" id="cluster_61354584_7623094020_7629652945" programID="0" phase="3" state="rrGGrrG"/>
    <tlsState time="1576.00" id="cluster_61354584_7623094020_7629652945" programID="0" phase="4" state="rrGGrrr"/>
    <tlsState time="1581.00" id="cluster_61354584_7623094020_7629652945" programID="0" phase="5" state="rryyrrr"/>
    <tlsState time="1584.00" id="cluster_61354584_7623094020_7629652945" programID="0" phase="0" state="ggrrGGr"/>
    <tlsState time="1589.00" id="cluster_61354584_7623094020_7629652945" programID="0" phase="1" state="ggrrrrr"/>
    <tlsState time="1594.00" id="cluster_61354584_7623094020_7629652945" programID="0" phase="2" state="yyrrrrr"/>
    <tlsState time="1597.00" id="cluster_61354584_7623094020_7629652945" programID="0" phase="3" state="rrGGrrG"/>
    <tlsState time="1602.00" id="cluster_61354584_7623094020_7629652945" programID="0" phase="4" state="rrGGrrr"/>
    <tlsState time="1607.00" id="cluster_61354584_7623094020_7629652945" programID="0" phase="5" state="rryyrrr"/>
    <tlsState time="1610.00" id="cluster_61354584_7623094020_7629652945" programID="0" phase="0" state="ggrrGGr"/>
</tlsStates>
